deutschland/bundestag_lobbyregister/__init__.py
deutschland/bundestag_lobbyregister/api/__init__.py
deutschland/bundestag_lobbyregister/api/default_api.py
deutschland/bundestag_lobbyregister/api_client.py
deutschland/bundestag_lobbyregister/apis/__init__.py
deutschland/bundestag_lobbyregister/configuration.py
deutschland/bundestag_lobbyregister/exceptions.py
deutschland/bundestag_lobbyregister/model/__init__.py
deutschland/bundestag_lobbyregister/model/activity.py
deutschland/bundestag_lobbyregister/model/address.py
deutschland/bundestag_lobbyregister/model/address_country.py
deutschland/bundestag_lobbyregister/model/client_organization.py
deutschland/bundestag_lobbyregister/model/detailed_search_results.py
deutschland/bundestag_lobbyregister/model/detailed_search_results_search_parameters.py
deutschland/bundestag_lobbyregister/model/donator.py
deutschland/bundestag_lobbyregister/model/donator_donation_euro.py
deutschland/bundestag_lobbyregister/model/entry.py
deutschland/bundestag_lobbyregister/model/entry_account.py
deutschland/bundestag_lobbyregister/model/entry_employee_count.py
deutschland/bundestag_lobbyregister/model/entry_financial_expenses_euro.py
deutschland/bundestag_lobbyregister/model/facet.py
deutschland/bundestag_lobbyregister/model/field_of_interest.py
deutschland/bundestag_lobbyregister/model/legal_form.py
deutschland/bundestag_lobbyregister/model/legal_representative.py
deutschland/bundestag_lobbyregister/model/legislative_project.py
deutschland/bundestag_lobbyregister/model/lobbyist_identity.py
deutschland/bundestag_lobbyregister/model/media.py
deutschland/bundestag_lobbyregister/model/media_media.py
deutschland/bundestag_lobbyregister/model/named_employee.py
deutschland/bundestag_lobbyregister/model/number_range.py
deutschland/bundestag_lobbyregister/model/search_result.py
deutschland/bundestag_lobbyregister/model/sort_order.py
deutschland/bundestag_lobbyregister/model_utils.py
deutschland/bundestag_lobbyregister/models/__init__.py
de_bundestag_lobbyregister-0.1.0.dist-info/WHEEL
de_bundestag_lobbyregister-0.1.0.dist-info/METADATA
de_bundestag_lobbyregister-0.1.0.dist-info/RECORD
